pyideogram/__init__.py
pyideogram/dataloader.py
pyideogram/ideogram.py
pyideogram/matplotlib_extension.py
pyideogram/misc.py
pyideogram/tracks.py
pyideogram/annotation/MANE38_chr1.pickle.xz
pyideogram/annotation/MANE38_chr10.pickle.xz
pyideogram/annotation/MANE38_chr11.pickle.xz
pyideogram/annotation/MANE38_chr12.pickle.xz
pyideogram/annotation/MANE38_chr13.pickle.xz
pyideogram/annotation/MANE38_chr14.pickle.xz
pyideogram/annotation/MANE38_chr15.pickle.xz
pyideogram/annotation/MANE38_chr16.pickle.xz
pyideogram/annotation/MANE38_chr17.pickle.xz
pyideogram/annotation/MANE38_chr18.pickle.xz
pyideogram/annotation/MANE38_chr19.pickle.xz
pyideogram/annotation/MANE38_chr2.pickle.xz
pyideogram/annotation/MANE38_chr20.pickle.xz
pyideogram/annotation/MANE38_chr21.pickle.xz
pyideogram/annotation/MANE38_chr22.pickle.xz
pyideogram/annotation/MANE38_chr3.pickle.xz
pyideogram/annotation/MANE38_chr4.pickle.xz
pyideogram/annotation/MANE38_chr5.pickle.xz
pyideogram/annotation/MANE38_chr6.pickle.xz
pyideogram/annotation/MANE38_chr7.pickle.xz
pyideogram/annotation/MANE38_chr8.pickle.xz
pyideogram/annotation/MANE38_chr9.pickle.xz
pyideogram/annotation/MANE38_chrX.pickle.xz
pyideogram/annotation/MANE38_chrY.pickle.xz
pyideogram/annotation/cytoBands.pickle.xz
pyideogram-0.1.1.dist-info/licenses/LICENSE
pyideogram-0.1.1.dist-info/METADATA
pyideogram-0.1.1.dist-info/WHEEL
pyideogram-0.1.1.dist-info/top_level.txt
pyideogram-0.1.1.dist-info/RECORD
