Metadata-Version: 2.4
Name: pyideogram
Version: 0.1.1
Summary: plot ideograms in matplotlib
Author: Balthasar Schlotmann
License:                    GNU LESSER GENERAL PUBLIC LICENSE
Project-URL: Homepage, https://github.com/Balthasar-eu/pyideogram
Project-URL: Bug Tracker, https://github.com/Balthasar-eu/pyideogram/issues
Classifier: Development Status :: 4 - Beta
Classifier: Programming Language :: Python :: 3.10
Classifier: Operating System :: OS Independent
Classifier: License :: OSI Approved :: GNU Lesser General Public License v3 (LGPLv3)
Requires-Python: >=3.10
License-File: LICENSE
Requires-Dist: matplotlib
Requires-Dist: numpy
Provides-Extra: test
Requires-Dist: pytest; extra == "test"
Dynamic: license-file
